tests/__init__.py
tests/test_cli.py
youtube2mp3/__init__.py
youtube2mp3/cli.py
youtube2mp3/options.py
youtube2mp3-2.0.7.dist-info/LICENSE.txt
youtube2mp3-2.0.7.dist-info/METADATA
youtube2mp3-2.0.7.dist-info/WHEEL
youtube2mp3-2.0.7.dist-info/entry_points.txt
youtube2mp3-2.0.7.dist-info/top_level.txt
youtube2mp3-2.0.7.dist-info/RECORD
