Metadata-Version: 2.1
Name: youtube2mp3
Version: 2.0.7
Summary: Commandline tool to convert youtube videos to tagged mp3 files
Home-page: https://github.com/pfitzer/youtube2mp3.git
Author: Michael Pfister
Author-email: michael@mp-development.de
License: MIT
Keywords: youtube mp3
Classifier: Development Status :: 5 - Production/Stable
Classifier: License :: OSI Approved :: MIT License
Classifier: Environment :: Console
Classifier: Intended Audience :: End Users/Desktop
Classifier: Programming Language :: Python :: 3.10
Classifier: Programming Language :: Python :: 3.11
Classifier: Programming Language :: Python :: 3.12
Classifier: Topic :: Multimedia :: Video :: Conversion
Requires-Python: ~=3.10, <4
License-File: LICENSE.txt
Requires-Dist: yt-dlp>=2024.9.27
Requires-Dist: mutagen>=1.47.0
